HISTORY.txt
README.txt
setup.py
version.txt
collective/__init__.py
collective.recipe.mxzopeda.egg-info/PKG-INFO
collective.recipe.mxzopeda.egg-info/SOURCES.txt
collective.recipe.mxzopeda.egg-info/dependency_links.txt
collective.recipe.mxzopeda.egg-info/entry_points.txt
collective.recipe.mxzopeda.egg-info/namespace_packages.txt
collective.recipe.mxzopeda.egg-info/requires.txt
collective.recipe.mxzopeda.egg-info/top_level.txt
collective.recipe.mxzopeda.egg-info/zip-safe
collective/recipe/__init__.py
collective/recipe/mxzopeda/__init__.py