Metadata-Version: 1.0
Name: collective.recipe.mxzopeda
Version: 0.1
Summary: A buildout recipe to install eGenix mx.ODBC.ZopeDA and a licence
Home-page: http://svn.plone.org/svn/collective/buildout/collective.recipe.mxzopeda
Author: Zest Software, Jarn
Author-email: info@zestsoftware.nl
License: GPL
Keywords: build mx.ODBC mx.ODBC ZopeDA
Platform: UNKNOWN
Classifier: Development Status :: 3 - Alpha
Classifier: Environment :: Plugins
Classifier: Intended Audience :: System Administrators
Classifier: Framework :: Buildout
Classifier: License :: OSI Approved :: GNU General Public License (GPL)
Classifier: Programming Language :: Python
Classifier: Topic :: Database
Classifier: Topic :: System :: Installation/Setup
Classifier: Topic :: Software Development :: Libraries :: Python Modules
